odoo/addons/stock_whole_kit_constraint/README.rst
odoo/addons/stock_whole_kit_constraint/__init__.py
odoo/addons/stock_whole_kit_constraint/__manifest__.py
odoo/addons/stock_whole_kit_constraint/i18n/es.po
odoo/addons/stock_whole_kit_constraint/i18n/it.po
odoo/addons/stock_whole_kit_constraint/i18n/stock_whole_kit_constraint.pot
odoo/addons/stock_whole_kit_constraint/models/__init__.py
odoo/addons/stock_whole_kit_constraint/models/product_template.py
odoo/addons/stock_whole_kit_constraint/models/stock_move.py
odoo/addons/stock_whole_kit_constraint/models/stock_picking.py
odoo/addons/stock_whole_kit_constraint/readme/CONFIGURE.rst
odoo/addons/stock_whole_kit_constraint/readme/CONTRIBUTORS.rst
odoo/addons/stock_whole_kit_constraint/readme/DESCRIPTION.rst
odoo/addons/stock_whole_kit_constraint/readme/USAGE.rst
odoo/addons/stock_whole_kit_constraint/static/description/icon.png
odoo/addons/stock_whole_kit_constraint/static/description/index.html
odoo/addons/stock_whole_kit_constraint/tests/__init__.py
odoo/addons/stock_whole_kit_constraint/tests/test_stock_whole_kit_constraint.py
odoo/addons/stock_whole_kit_constraint/views/product_template_views.xml
odoo_addon_stock_whole_kit_constraint-15.0.1.0.0.5.dist-info/METADATA
odoo_addon_stock_whole_kit_constraint-15.0.1.0.0.5.dist-info/WHEEL
odoo_addon_stock_whole_kit_constraint-15.0.1.0.0.5.dist-info/top_level.txt
odoo_addon_stock_whole_kit_constraint-15.0.1.0.0.5.dist-info/RECORD
